{
"c311-3": {
"name": "CRTS J204448.9-033832",
"other": "2MASS J, GALEX J",
"desig": "GSC2.3",
"gdr3": 6915079388750374912,
"epphot": false,
"coord": "20 44 48.9462 -03 38 33.225",
"coordeg": [311.20394, -3.64256],
"type": "EA",
"max": 14.30,
"min": 14.86,
"min2": 14.75,
"d": 0.02,
"d2": 0.023,
"system": "r",
"period": 6.67167,
"epoch": 2456166.88,
"2ndmin": 0.383,
"etype": "min",
"sp": "",
"comm": "Eccentric system. Min II = 14.75 r at phase 0.383, duration 2.3% //period determination in literature: 2019ApJS..244...43Z",
"vsxoid": 392212,
"asaslimold": 0.07,
"atlaslim": {"o": 0.05, "c": 0.04},
"asaslim": {"V": 0.045, "g": 0.045},
"pslim": 0.1,
"atlasfnam": "c311-3-atlas.txt",
"asasfnam": "c311-3-asas.csv",
"gaiadr3fnamz": "c311-3-gaiadr3.dat",
"crtsfnam": "c311-3-crts.csv",
"curveshift": true,
"clrshift": {"g": 0.72, "psg": 0.13, "r": 0, "psr": 0, "i": -0.24, "psi": -0.35, "psz": -0.2, "psy": -0.2,
             "o": -0.06, "c": 0.37, "V": 0.32, "asasg": 0.74, "G": 0.05, "CV": 0.03},
"plot": {"ztffilt": "gri", "psfilt": "", "atlasfilt": "oc", "asasfilt": "",
  "atlaslim": 0.2, "atlaselw": 0.26, "xmal": 500, "xmil": 170, "ymil": 0.02,
  "asasms": 4.5,
  "zms": 4,
  "gms": 4,
  "psms": 6,
  "atlasms": {"o": 2, "c": 2},
  "atledgclr": "darkred",
  "magl": 0.1,
  "xedges": 90,
  "legz": "lower left",
  "zoom": {
    "xlim": [-0.020, 0.411],
    "xmalp": 0.1,
    "xmilp": 0.02
  },
  "xlim": [-0.05, 1],
  "ylim": [14.929, 14.21],
  "ylima": [14.929, 14.21]
}
}}