{
"gds0746": {
"name": "GDS J0746473-260551",
"other": "ASASSN-V J074647.34-260551.6, ATO J116.6972-26.0976, GSC2.3 S60Z065244",
"desig": "USNO-B1.0 0639-0155394, [SBG2019] J116.6972-26.0976",
"gdr3": 5601911383036697856,
"epphot": true,
"veb": true,
"vst": false,
"tic": 776753359,
"coord": "07 46 47.331 -26 05 51.59",
"coordeg": [116.6972125, -26.097664],
"type": "EA/HW",
"max": 16.63,
"min": 18.8,
"d": 0.13,
"2ndmin": 0.5,
"system": "r",
"period": 0.13709699,
"epoch": 2457090.8673,
"etype": "min",
"sp": "B",
"spref": "2023A&A...674A..26C",
"teff": 9999,
"logg": 4.57,
"r": 2709,
"rp": 2795,
"G": 16.51,
"BP-RP": -0.055,
"comm": "",
"atlasnam": "gds0746",
"atlaslim": {"o": 0.17, "c": 0.16},
"gaiadr3nam": "gds0746",
"vsxoid": 423026,
"lc": "hw/gds0746-ps1-atl-gds-gdr3-ph.png",
"curveshift": true,
"clrshift": {"g": -0.15, "psg": -0.15, "r": 0.04, "psr": 0.04, "i": 0.2, "psi": 0.2, "psz": 0.3, "psy": 0.4,
             "o": 0.06, "c": -0.12, "G": -0.14},
"plot": {"ztffilt": "", "psfilt": "grizy", "atlasfilt": "oc", "gdsfilt": "r",
  "psms": 7, "atlasms": {"o": 2, "c": 2}, "elw": 1, "gms": 7.5,
  "atledgclr": "#922",
  "xmal": 800, "xmil": 100, "ymil": 0.05,
  "xedges": 100,
  "xlim": [-0.25, 1],
  "zoom": {
    "xlim": [-0.11, 0.11],
    "xmalp": 0.02,
    "xmilp": 0.01
  },
  "ylim": [18.94, 16.39],
  "ylima": [18.94, 16.39]
}
}}